{"title":"Depeche Mode - Stripped (Live Rock Am Ring 2006)","uid":3492876,"size":51351726,"categoryP":"video","categoryS":"music_videos","magnet":"?xt=urn:btih:040db37c77fd83354b95c8cdb7bfee47a7154838&amp;dn=Depeche+Mode+-+Stripped+%28Live+Rock+Am+Ring+2006%29&amp;tr=udp%3A%2F%2Ftracker.openbittorrent.com%3A80&amp;tr=udp%3A%2F%2Fopen.demonii.com%3A1337&amp;tr=udp%3A%2F%2Ftracker.coppersurfer.tk%3A6969&amp;tr=udp%3A%2F%2Fexodus.desync.com%3A6969","seeders":0,"leechers":1,"uploader":"RosaMannen","files":1,"time":1149628549,"description":"Depeche Mode live at Rock Am Ring 2006. This is propably my all-time favourite band.\nGreat perfomance! Don&amp;#039;t miss this!\n\n\n.ooOO ROSA MANNEN 2006 OOoo.\t","torrent":{"xt":"urn:btih:040db37c77fd83354b95c8cdb7bfee47a7154838","amp;dn":"Depeche+Mode+-+Stripped+%28Live+Rock+Am+Ring+2006%29","amp;tr":["udp%3A%2F%2Ftracker.openbittorrent.com%3A80","udp%3A%2F%2Fopen.demonii.com%3A1337","udp%3A%2F%2Ftracker.coppersurfer.tk%3A6969","udp%3A%2F%2Fexodus.desync.com%3A6969"],"infoHash":"040db37c77fd83354b95c8cdb7bfee47a7154838","infoHashBuffer":{"type":"Buffer","data":[4,13,179,124,119,253,131,53,75,149,200,205,183,191,238,71,167,21,72,56]},"announce":[],"urlList":[]}}