{"title":"Driver ps2 nrg","uid":3302998,"size":742392552,"categoryP":"games","categoryS":"psx","magnet":"?xt=urn:btih:0efc3210a224c23a3dd94cf9ba8cbde0b30a77e4&amp;dn=Driver+ps2+nrg&amp;tr=udp%3A%2F%2Ftracker.openbittorrent.com%3A80&amp;tr=udp%3A%2F%2Fopen.demonii.com%3A1337&amp;tr=udp%3A%2F%2Ftracker.coppersurfer.tk%3A6969&amp;tr=udp%3A%2F%2Fexodus.desync.com%3A6969","seeders":0,"leechers":1,"uploader":"Riclars","files":1,"time":1111087077,"description":"Bilspel till ps2 i neroformat","torrent":{"xt":"urn:btih:0efc3210a224c23a3dd94cf9ba8cbde0b30a77e4","amp;dn":"Driver+ps2+nrg","amp;tr":["udp%3A%2F%2Ftracker.openbittorrent.com%3A80","udp%3A%2F%2Fopen.demonii.com%3A1337","udp%3A%2F%2Ftracker.coppersurfer.tk%3A6969","udp%3A%2F%2Fexodus.desync.com%3A6969"],"infoHash":"0efc3210a224c23a3dd94cf9ba8cbde0b30a77e4","infoHashBuffer":{"type":"Buffer","data":[14,252,50,16,162,36,194,58,61,217,76,249,186,140,189,224,179,10,119,228]},"announce":[],"urlList":[]}}