{"title":"BRUCE HORNSBY - HARBOR LIGHTS","uid":3425737,"size":44353264,"categoryP":"audio","categoryS":"music","magnet":"?xt=urn:btih:2d4e980f1f3c47569e2d15b07975484d65d284ad&amp;dn=BRUCE+HORNSBY+-+HARBOR+LIGHTS&amp;tr=udp%3A%2F%2Ftracker.openbittorrent.com%3A80&amp;tr=udp%3A%2F%2Fopen.demonii.com%3A1337&amp;tr=udp%3A%2F%2Ftracker.coppersurfer.tk%3A6969&amp;tr=udp%3A%2F%2Fexodus.desync.com%3A6969","seeders":0,"leechers":1,"uploader":"marcelino","files":10,"time":1135887125,"description":"http://tracker.prq.to/announce","torrent":{"xt":"urn:btih:2d4e980f1f3c47569e2d15b07975484d65d284ad","amp;dn":"BRUCE+HORNSBY+-+HARBOR+LIGHTS","amp;tr":["udp%3A%2F%2Ftracker.openbittorrent.com%3A80","udp%3A%2F%2Fopen.demonii.com%3A1337","udp%3A%2F%2Ftracker.coppersurfer.tk%3A6969","udp%3A%2F%2Fexodus.desync.com%3A6969"],"infoHash":"2d4e980f1f3c47569e2d15b07975484d65d284ad","infoHashBuffer":{"type":"Buffer","data":[45,78,152,15,31,60,71,86,158,45,21,176,121,117,72,77,101,210,132,173]},"announce":[],"urlList":[]}}