{"title":"A.PERFECT.CIRCLE.eMOTIVe","uid":3406206,"size":115894848,"categoryP":"audio","categoryS":"music","magnet":"?xt=urn:btih:368e95f0edfdb244e36592988da37cdbda18a47b&amp;dn=A.PERFECT.CIRCLE.eMOTIVe&amp;tr=udp%3A%2F%2Ftracker.openbittorrent.com%3A80&amp;tr=udp%3A%2F%2Fopen.demonii.com%3A1337&amp;tr=udp%3A%2F%2Ftracker.coppersurfer.tk%3A6969&amp;tr=udp%3A%2F%2Fexodus.desync.com%3A6969","seeders":0,"leechers":1,"uploader":"Deckard0","files":12,"time":1131325049,"description":"A.PERFECT.CIRCLE.eMOTIVe","torrent":{"xt":"urn:btih:368e95f0edfdb244e36592988da37cdbda18a47b","amp;dn":"A.PERFECT.CIRCLE.eMOTIVe","amp;tr":["udp%3A%2F%2Ftracker.openbittorrent.com%3A80","udp%3A%2F%2Fopen.demonii.com%3A1337","udp%3A%2F%2Ftracker.coppersurfer.tk%3A6969","udp%3A%2F%2Fexodus.desync.com%3A6969"],"infoHash":"368e95f0edfdb244e36592988da37cdbda18a47b","infoHashBuffer":{"type":"Buffer","data":[54,142,149,240,237,253,178,68,227,101,146,152,141,163,124,219,218,24,164,123]},"announce":[],"urlList":[]}}