{"title":"Pussyman Asian Assault 2","uid":3314351,"size":932762964,"categoryP":"porn","categoryS":"movies","magnet":"?xt=urn:btih:408b0969bd16f9c034ff125140e9336d920e2174&amp;dn=Pussyman+Asian+Assault+2&amp;tr=udp%3A%2F%2Ftracker.openbittorrent.com%3A80&amp;tr=udp%3A%2F%2Fopen.demonii.com%3A1337&amp;tr=udp%3A%2F%2Ftracker.coppersurfer.tk%3A6969&amp;tr=udp%3A%2F%2Fexodus.desync.com%3A6969","seeders":0,"leechers":2,"uploader":"zippydedodah","files":2,"time":1113068078,"description":"for review, covers, etc...\n\nhttp://www.iafd.com/title.rme/title=Pussyman's+Asian+Assault+2/year=2004/Pussyman's_Asian_Assault_2.htm","torrent":{"xt":"urn:btih:408b0969bd16f9c034ff125140e9336d920e2174","amp;dn":"Pussyman+Asian+Assault+2","amp;tr":["udp%3A%2F%2Ftracker.openbittorrent.com%3A80","udp%3A%2F%2Fopen.demonii.com%3A1337","udp%3A%2F%2Ftracker.coppersurfer.tk%3A6969","udp%3A%2F%2Fexodus.desync.com%3A6969"],"infoHash":"408b0969bd16f9c034ff125140e9336d920e2174","infoHashBuffer":{"type":"Buffer","data":[64,139,9,105,189,22,249,192,52,255,18,81,64,233,51,109,146,14,33,116]},"announce":[],"urlList":[]}}