{"title":"bitplane - duality","uid":3406184,"size":76769642,"categoryP":"audio","categoryS":"music","magnet":"?xt=urn:btih:474cbdd11efff38640d648d85a46f15ed9fde675&amp;dn=bitplane+-+duality&amp;tr=udp%3A%2F%2Ftracker.openbittorrent.com%3A80&amp;tr=udp%3A%2F%2Fopen.demonii.com%3A1337&amp;tr=udp%3A%2F%2Ftracker.coppersurfer.tk%3A6969&amp;tr=udp%3A%2F%2Fexodus.desync.com%3A6969","seeders":0,"leechers":0,"uploader":"bazkie","files":13,"time":1131322609,"description":"laidback drumnbass album 2005\nencoded with lame high quality","torrent":{"xt":"urn:btih:474cbdd11efff38640d648d85a46f15ed9fde675","amp;dn":"bitplane+-+duality","amp;tr":["udp%3A%2F%2Ftracker.openbittorrent.com%3A80","udp%3A%2F%2Fopen.demonii.com%3A1337","udp%3A%2F%2Ftracker.coppersurfer.tk%3A6969","udp%3A%2F%2Fexodus.desync.com%3A6969"],"infoHash":"474cbdd11efff38640d648d85a46f15ed9fde675","infoHashBuffer":{"type":"Buffer","data":[71,76,189,209,30,255,243,134,64,214,72,216,90,70,241,94,217,253,230,117]},"announce":[],"urlList":[]}}