{"title":"Belgian SWAT","uid":3283033,"size":69616832,"categoryP":"video","categoryS":"tv_shows","magnet":"?xt=urn:btih:484f4edf4666635f7b9cb0b8edad6d7609dee152&amp;dn=Belgian+SWAT&amp;tr=udp%3A%2F%2Ftracker.openbittorrent.com%3A80&amp;tr=udp%3A%2F%2Fopen.demonii.com%3A1337&amp;tr=udp%3A%2F%2Ftracker.coppersurfer.tk%3A6969&amp;tr=udp%3A%2F%2Fexodus.desync.com%3A6969","seeders":0,"leechers":1,"uploader":"zablam","files":1,"time":1107007606,"description":"Belgian Swat team training.","torrent":{"xt":"urn:btih:484f4edf4666635f7b9cb0b8edad6d7609dee152","amp;dn":"Belgian+SWAT","amp;tr":["udp%3A%2F%2Ftracker.openbittorrent.com%3A80","udp%3A%2F%2Fopen.demonii.com%3A1337","udp%3A%2F%2Ftracker.coppersurfer.tk%3A6969","udp%3A%2F%2Fexodus.desync.com%3A6969"],"infoHash":"484f4edf4666635f7b9cb0b8edad6d7609dee152","infoHashBuffer":{"type":"Buffer","data":[72,79,78,223,70,102,99,95,123,156,176,184,237,173,109,118,9,222,225,82]},"announce":[],"urlList":[]}}