{"title":"Nieuw in de Tipparade week 12-13-14(2006)","uid":3467616,"size":110352303,"categoryP":"audio","categoryS":"music","magnet":"?xt=urn:btih:568c1c3e3d5f62976337ca196f86cec11d85a059&amp;dn=Nieuw+in+de+Tipparade+week+12-13-14%282006%29&amp;tr=udp%3A%2F%2Ftracker.openbittorrent.com%3A80&amp;tr=udp%3A%2F%2Fopen.demonii.com%3A1337&amp;tr=udp%3A%2F%2Ftracker.coppersurfer.tk%3A6969&amp;tr=udp%3A%2F%2Fexodus.desync.com%3A6969","seeders":0,"leechers":0,"uploader":"NLhappy","files":23,"time":1144371488,"description":"*******************************************************************************\n                  Nieuw in de Tipparade week 12-13-14(2006)\n*******************************************************************************\n\n-------------------------------------------------------------------------------\n                             General Information\n-------------------------------------------------------------------------------\nType.................: Music\nFile Validation......: SFV\n\nYear.................: 2006\nGenre................: top 40\nNumber of Songs......: 21\n\nAudio Format.........: MP3\nEncoder..............: LAME\nBitrate..............: 192 \nHz...................: 44,100\n\n\n-------------------------------------------------------------------------------\n                              Post Information\n-------------------------------------------------------------------------------\nPosted by............: NLhappy\n\n-------------------------------------------------------------------------------\n                                Release Notes\n-------------------------------------------------------------------------------\nTracklist:\n\n12-23 Mary J Blige Featuring U2- One\n12-24 Armin Van Buuren - Sail\n12-25 Katie Melua - Spider&amp;#039;s Web\n12-26 Jamie Foxx Feat. Ludacris - Unpredictable\n12-27 Filterfunk - S.O.S. (Message In A Bottle)\n12-28 Kubb -Wicked Soul\n12-29 Roy Gates-Lose Myself\n12-30 Rihanna- S.O.S. (Rescue Me)\n13-26 Treble - Amambanda\n13-27 Do - Follow Me\n13-28 Nick &amp; Simon - Steeds Weer\n13-29 Don Diablo - Who&amp;#039;s Your Daddy (Radio Edit)\n13-30 Bizzey - The Fur\n14-16 Lange Frans &amp; Baas B Feat. Brutus &amp; Tim - Ik Wacht Al Zo Lang\n14-24 Bob Sinclar Feat. Steve Edwards - World Hold On\n14-25 Red Hot Chili Pepers - Dani California\n14-26 The Feeling - Sewn\n14-27 Clouseau - Ik Zie De Hemel\n14-28  Chris Brown - Yo (Excuse Me Miss)\n14-29 Brace - Drijfzand (Laat Me Niet Alleen)\n14-30 LL Cool J Feat. J Lo - Control Myself (Radio Edit)","torrent":{"xt":"urn:btih:568c1c3e3d5f62976337ca196f86cec11d85a059","amp;dn":"Nieuw+in+de+Tipparade+week+12-13-14%282006%29","amp;tr":["udp%3A%2F%2Ftracker.openbittorrent.com%3A80","udp%3A%2F%2Fopen.demonii.com%3A1337","udp%3A%2F%2Ftracker.coppersurfer.tk%3A6969","udp%3A%2F%2Fexodus.desync.com%3A6969"],"infoHash":"568c1c3e3d5f62976337ca196f86cec11d85a059","infoHashBuffer":{"type":"Buffer","data":[86,140,28,62,61,95,98,151,99,55,202,25,111,134,206,193,29,133,160,89]},"announce":[],"urlList":[]}}