{"title":"Madonna-Hung_Up-PROPER-SVCD-2005-SE","uid":3405235,"size":112557831,"categoryP":"video","categoryS":"music_videos","magnet":"?xt=urn:btih:56e628f92dae7e92d5598504782eb096744c5a58&amp;dn=Madonna-Hung_Up-PROPER-SVCD-2005-SE&amp;tr=udp%3A%2F%2Ftracker.openbittorrent.com%3A80&amp;tr=udp%3A%2F%2Fopen.demonii.com%3A1337&amp;tr=udp%3A%2F%2Ftracker.coppersurfer.tk%3A6969&amp;tr=udp%3A%2F%2Fexodus.desync.com%3A6969","seeders":0,"leechers":0,"uploader":"PudradFjolla","files":3,"time":1131137816,"description":"????????????????????????????????????????????????????????????????????????????\n??????&amp;Iuml;&amp;Iuml;&amp;Iuml;&amp;Iuml;&amp;Iuml;&amp;Iuml;&amp;Iuml;&amp;Iuml;&amp;Iuml;&amp;Iuml;&amp;Iuml;&amp;Iuml;&amp;Iuml;&amp;Iuml;&amp;Iuml;&amp;Iuml;&amp;Iuml;&amp;Iuml;&amp;Iuml;&amp;Iuml;&amp;Iuml;&amp;Iuml;&amp;Iuml;&amp;Iuml;&amp;Iuml;&amp;Iuml;&amp;Iuml;&amp;Iuml;&amp;Iuml;&amp;Iuml;&amp;Iuml;&amp;Iuml;&amp;Iuml;&amp;Iuml;&amp;Iuml;&amp;Iuml;&amp;Iuml;&amp;Iuml;&amp;Iuml;&amp;Iuml;&amp;Iuml;&amp;Iuml;&amp;Iuml;&amp;Iuml;&amp;Iuml;&amp;Iuml;&amp;Iuml;&amp;Iuml;&amp;Iuml;&amp;Iuml;&amp;Iuml;&amp;Iuml;&amp;Iuml;&amp;Iuml;&amp;Iuml;&amp;Iuml;&amp;Iuml;&amp;Iuml;&amp;Iuml;&amp;Iuml;&amp;Iuml;&amp;Iuml;&amp;Iuml;&amp;Iuml;??????\n????????????????????????????????????????????????????????????????????????????\n??&amp;Iacute;                                                                      &amp;Agrave;??\n???                        ??????                                        ???\n???                   ??????????????                                     ???\n???                 ???????  ????????   ???????????                      ???\n???     ????????   ?????          ???????????????????     ?????????      ???\n???   ???????????????              ???????      ??????   ???????????     ???\n???   ???    ????????              ??????        ?????  ???    ??????    ???\n???   ???    ???????   ?????      ????     ??????????   ???    ??????    ???\n???   ??????????????  ??? ?????  ?????    ????????????  ????????????     ???\n???     ???????  ???  ???? ???????????     ?????????????  ?????????      ???\n???      ????    ???   ???????   ?????            ??????   ?????         ???\n???    ????????? ????              ????       ??????????  ?????????      ???\n???   ????????????????????        ????       ???????????????????????     ???\n???   ???    ?????????????       ?????       ????   ???????    ??????    ???\n???   ???    ??????  ?????       ?????              ??????     ??????    ???\n???   ??????????????             ???????             ????????????????    ???\n???     ????????????            ?????????          ?????? ??????????     ???\n???      ????    ??????        ??????? ????????  ????????  ????????      ???\n???               ????????????????      ??????????????                   ???\n???                ????????????           ?????????                      ???\n??&amp;Euml;                                                                      &amp;cent;??\n????????????????????????????????????????????????????????????????????????????\n??????&amp;Iuml;&amp;Iuml;&amp;Iuml;&amp;Iuml;&amp;Iuml;&amp;Iuml;&amp;Iuml;&amp;Iuml;&amp;Iuml;&amp;Iuml;&amp;Iuml;&amp;Iuml;&amp;Iuml;&amp;Iuml;&amp;Iuml;&amp;Iuml;&amp;Iuml;&amp;Iuml;&amp;Iuml;&amp;Iuml;&amp;Iuml;&amp;Iuml;&amp;Iuml;&amp;Iuml;&amp;Iuml;&amp;Iuml;&amp;Iuml;&amp;Iuml;&amp;Iuml;&amp;Iuml;&amp;Iuml;&amp;Iuml;&amp;Iuml;&amp;Iuml;&amp;Iuml;&amp;Iuml;&amp;Iuml;&amp;Iuml;&amp;Iuml;&amp;Iuml;&amp;Iuml;&amp;Iuml;&amp;Iuml;&amp;Iuml;&amp;Iuml;&amp;Iuml;&amp;Iuml;&amp;Iuml;&amp;Iuml;&amp;Iuml;&amp;Iuml;&amp;Iuml;&amp;Iuml;&amp;Iuml;&amp;Iuml;&amp;Iuml;&amp;Iuml;&amp;Iuml;&amp;Iuml;&amp;Iuml;&amp;Iuml;&amp;Iuml;&amp;Iuml;&amp;Iuml;??????\n????????????????????????????????????????????????????????????????????????????\n???????????? dOMiNATiNG tHE eLECTRONiCA mPEG-2 sCENE siNCE 2001  ???????????\n????????????         &amp;uml; SE - THE DEFENITION OF QUALITY! &amp;uml;         ???????????\n???????????? [ tHE pREMiERE aLL eLECTRONiCA mUSiC viDEO gROUP! ] ???????????\n???????????????????????  SECTION-E PROUDLY PRESENTS  ???????????????????????\n??&amp;Iacute;??????????????????????????????????????????????????????????????????????&amp;Agrave;??\n???&amp;atilde; Artist:................................................... Madonna &amp;Aacute;???\n???&amp;atilde; Title:.................................................... Hung Up &amp;Aacute;???\n???&amp;atilde; Filename:......................................................... &amp;Aacute;???\n???&amp;atilde; .............................. Madonna-Hung_Up-PROPER-SVCD-2005-SE &amp;Aacute;???\n???                                                                      ???\n???? Date:............... 28/10/2005 ??? Rip:.................. SE Crew ????\n???? Genre:................... Dance ??? Encode:............... SE Crew ????\n???? Combined Filesize:... 112.98 MB ??? Audio Source:..... VBRkbit MP3 ????\n???? Length:................... 5:27 ??? Audio Format:..... 224kbit MP2 ????\n???? Channel:............. Channel 4 ??? Video Source:.............. TV ????\n???? Resolution:............ 480x576 ??? Encoder:.................. CCE ????\n???? Type:................. PAL SVCD ??? Deinterlace Method:.... Manual ????\n???? Aspect Ratio:.............. 4:3 ??? Video Type:........ FullScreen ????\n??&amp;Euml;                                                                      &amp;cent;??\n????????????????????????????????????????????????????????????????????????????\n???&amp;uml;&amp;uml;&amp;uml;&amp;uml;&amp;uml;&amp;uml;&amp;uml;&amp;uml;&amp;uml;&amp;uml;&amp;uml;&amp;uml;&amp;uml;&amp;uml;&amp;uml;&amp;uml;&amp;uml;&amp;uml;&amp;uml;&amp;uml;&amp;uml;&amp;uml;&amp;uml; R E L E A S E   I N F O &amp;uml;&amp;uml;&amp;uml;&amp;uml;&amp;uml;&amp;uml;&amp;uml;&amp;uml;&amp;uml;&amp;uml;&amp;uml;&amp;uml;&amp;uml;&amp;uml;&amp;uml;&amp;uml;&amp;uml;&amp;uml;&amp;uml;&amp;uml;&amp;uml;&amp;uml;???\n????????????????????????????????????????????????????????????????????????????\n??                                                                        ??\n??  In this vid Madonna breathes new life into DDR at London's            ??\n??  Trocadero :P                                                          ??\n??                                                                        ??\n??  Enjoy.                                                                ??\n??                                                                        ??\n????????                                                  SE Crew   ????????\n????????????????????????????????????????????????????????????????????????????\n???&amp;uml;&amp;uml;&amp;uml;&amp;uml;&amp;uml;&amp;uml;&amp;uml;&amp;uml;&amp;uml;&amp;uml;&amp;uml;&amp;uml;&amp;uml;&amp;uml;&amp;uml;&amp;uml;&amp;uml;&amp;uml;&amp;uml;&amp;uml;&amp;uml;&amp;uml;&amp;uml;&amp;uml; O T H E R  N O T E S &amp;uml;&amp;uml;&amp;uml;&amp;uml;&amp;uml;&amp;uml;&amp;uml;&amp;uml;&amp;uml;&amp;uml;&amp;uml;&amp;uml;&amp;uml;&amp;uml;&amp;uml;&amp;uml;&amp;uml;&amp;uml;&amp;uml;&amp;uml;&amp;uml;&amp;uml;&amp;uml;&amp;uml;???\n????????????????????????????????????????????????????????????????????????????\n??                                                                        ??\n??   Proper of WHQRE release which is NTSC, here you got a PAL            ??\n??   progressive one.                                                     ??\n??   Having a nice source we've decided to make one thing more in         ??\n??   order to promote XViD: release SVCD and XViD rip of the same vid     ??\n??   to let you compare and jump to an obvious conclusion.                ??\n??   Make sure you download the XViD one!!                                ??\n??                                                                        ??\n????????                                                  SE Crew   ????????\n????????????????????????????????????????????????????????????????????????????\n???&amp;uml;&amp;uml;&amp;uml;&amp;uml;&amp;uml;&amp;uml;&amp;uml;&amp;uml;&amp;uml;&amp;uml;&amp;uml;&amp;uml;&amp;uml;&amp;uml;&amp;uml;&amp;uml;&amp;uml;&amp;uml;&amp;uml;&amp;uml;&amp;uml;&amp;uml;&amp;uml;&amp;uml;&amp;uml; G R O U P  I N F O &amp;uml;&amp;uml;&amp;uml;&amp;uml;&amp;uml;&amp;uml;&amp;uml;&amp;uml;&amp;uml;&amp;uml;&amp;uml;&amp;uml;&amp;uml;&amp;uml;&amp;uml;&amp;uml;&amp;uml;&amp;uml;&amp;uml;&amp;uml;&amp;uml;&amp;uml;&amp;uml;&amp;uml;&amp;uml;???\n????????????????????????????????????????????????????????????????????????????\n???                                                                      ???\n???   Section-E was formed in January of 2001 with the idea of having    ???\n???   a release group that focused entirely on electronica videos and    ???\n???   only on electronica videos, rather then being the typical group    ???\n???   that tries to cover all genres.                                    ???\n???                                                                      ???\n???   Now in late 2005 trying to make Xvid a popular format for music    ???\n???   videos.                                                            ???\n???                                                                      ???\n???                                 The Way It Should Be. [ SE Crew ]    ???\n??&amp;Euml;                                                                      &amp;cent;??\n????????????????\n????????????????????????????????????????????????????????????????????????????\n\n","torrent":{"xt":"urn:btih:56e628f92dae7e92d5598504782eb096744c5a58","amp;dn":"Madonna-Hung_Up-PROPER-SVCD-2005-SE","amp;tr":["udp%3A%2F%2Ftracker.openbittorrent.com%3A80","udp%3A%2F%2Fopen.demonii.com%3A1337","udp%3A%2F%2Ftracker.coppersurfer.tk%3A6969","udp%3A%2F%2Fexodus.desync.com%3A6969"],"infoHash":"56e628f92dae7e92d5598504782eb096744c5a58","infoHashBuffer":{"type":"Buffer","data":[86,230,40,249,45,174,126,146,213,89,133,4,120,46,176,150,116,76,90,88]},"announce":[],"urlList":[]}}