{"title":"A Perfect Circle - Judith","uid":3316762,"size":41271776,"categoryP":"video","categoryS":"music_videos","magnet":"?xt=urn:btih:5bfafef25a75a1ce13c8ee73816b5996673fe4b8&amp;dn=A+Perfect+Circle+-+Judith&amp;tr=udp%3A%2F%2Ftracker.openbittorrent.com%3A80&amp;tr=udp%3A%2F%2Fopen.demonii.com%3A1337&amp;tr=udp%3A%2F%2Ftracker.coppersurfer.tk%3A6969&amp;tr=udp%3A%2F%2Fexodus.desync.com%3A6969","seeders":0,"leechers":0,"uploader":"mickehan","files":1,"time":1113495952,"description":"A Perfect Circle - Judith","torrent":{"xt":"urn:btih:5bfafef25a75a1ce13c8ee73816b5996673fe4b8","amp;dn":"A+Perfect+Circle+-+Judith","amp;tr":["udp%3A%2F%2Ftracker.openbittorrent.com%3A80","udp%3A%2F%2Fopen.demonii.com%3A1337","udp%3A%2F%2Ftracker.coppersurfer.tk%3A6969","udp%3A%2F%2Fexodus.desync.com%3A6969"],"infoHash":"5bfafef25a75a1ce13c8ee73816b5996673fe4b8","infoHashBuffer":{"type":"Buffer","data":[91,250,254,242,90,117,161,206,19,200,238,115,129,107,89,150,103,63,228,184]},"announce":[],"urlList":[]}}