{"title":"Control Tutorial","uid":3493448,"size":2508550,"categoryP":"other","categoryS":"e_books","magnet":"?xt=urn:btih:632a931233c819f100e60cde6724dcdec642da00&amp;dn=Control+Tutorial&amp;tr=udp%3A%2F%2Ftracker.openbittorrent.com%3A80&amp;tr=udp%3A%2F%2Fopen.demonii.com%3A1337&amp;tr=udp%3A%2F%2Ftracker.coppersurfer.tk%3A6969&amp;tr=udp%3A%2F%2Fexodus.desync.com%3A6969","seeders":0,"leechers":1,"uploader":"newtonviet","files":12,"time":1149742464,"description":"Download this very good collection and many other Good Ebooks and Magazine about automation and process control here: http://www.haison.com.vn/Ebooks/","torrent":{"xt":"urn:btih:632a931233c819f100e60cde6724dcdec642da00","amp;dn":"Control+Tutorial","amp;tr":["udp%3A%2F%2Ftracker.openbittorrent.com%3A80","udp%3A%2F%2Fopen.demonii.com%3A1337","udp%3A%2F%2Ftracker.coppersurfer.tk%3A6969","udp%3A%2F%2Fexodus.desync.com%3A6969"],"infoHash":"632a931233c819f100e60cde6724dcdec642da00","infoHashBuffer":{"type":"Buffer","data":[99,42,147,18,51,200,25,241,0,230,12,222,103,36,220,222,198,66,218,0]},"announce":[],"urlList":[]}}