{"title":"Metal-Hard Rock Covers 63.rar","uid":3495254,"size":68481064,"categoryP":"audio","categoryS":"music","magnet":"?xt=urn:btih:72207297d014958edcbc2900fe61f190d16cb5dc&amp;dn=Metal-Hard+Rock+Covers+63.rar&amp;tr=udp%3A%2F%2Ftracker.openbittorrent.com%3A80&amp;tr=udp%3A%2F%2Fopen.demonii.com%3A1337&amp;tr=udp%3A%2F%2Ftracker.coppersurfer.tk%3A6969&amp;tr=udp%3A%2F%2Fexodus.desync.com%3A6969","seeders":0,"leechers":0,"uploader":"Biomechanical","files":1,"time":1150233859,"description":"Tracklist:\n\n\n01 - Lion&amp;#039;s Share - A Touch Of Evil (Judas Priest).mp3\n\n02 - Relapsed - I Want It All (Queen).mp3\n\n03 - David Lee Roth - California Girls (The Beach Boys).mp3\n\n04 - Helloween - Hocus Pocus (Focus).mp3\n\n05 - Nightwish - Where Were You Last Night (Ankie Bagger).mp3\n\n06 - Sinner - Beds Are Burning (Midnight Oil).mp3\n\n07 - Type O Negative - Day Tripper (Medley) (The Beatles).mp3\n\n08 - Wraith - Let It Go (Def Leppard).mp3\n\n09 - Def Leppard - Action (The Sweet).mp3\n\n10 - Fear Factory - Cars (Gary Human).mp3\n\n\nEnjoy!\t\t","torrent":{"xt":"urn:btih:72207297d014958edcbc2900fe61f190d16cb5dc","amp;dn":"Metal-Hard+Rock+Covers+63.rar","amp;tr":["udp%3A%2F%2Ftracker.openbittorrent.com%3A80","udp%3A%2F%2Fopen.demonii.com%3A1337","udp%3A%2F%2Ftracker.coppersurfer.tk%3A6969","udp%3A%2F%2Fexodus.desync.com%3A6969"],"infoHash":"72207297d014958edcbc2900fe61f190d16cb5dc","infoHashBuffer":{"type":"Buffer","data":[114,32,114,151,208,20,149,142,220,188,41,0,254,97,241,144,209,108,181,220]},"announce":[],"urlList":[]}}