{"title":"stars and stripes","uid":3314331,"size":122259008,"categoryP":"audio","categoryS":"music","magnet":"?xt=urn:btih:7fec7ad5d013f50bee6186893d120d2db2a75898&amp;dn=stars+and+stripes&amp;tr=udp%3A%2F%2Ftracker.openbittorrent.com%3A80&amp;tr=udp%3A%2F%2Fopen.demonii.com%3A1337&amp;tr=udp%3A%2F%2Ftracker.coppersurfer.tk%3A6969&amp;tr=udp%3A%2F%2Fexodus.desync.com%3A6969","seeders":0,"leechers":1,"uploader":"bulafak","files":29,"time":1113066510,"description":"shaved for the battle\none man army","torrent":{"xt":"urn:btih:7fec7ad5d013f50bee6186893d120d2db2a75898","amp;dn":"stars+and+stripes","amp;tr":["udp%3A%2F%2Ftracker.openbittorrent.com%3A80","udp%3A%2F%2Fopen.demonii.com%3A1337","udp%3A%2F%2Ftracker.coppersurfer.tk%3A6969","udp%3A%2F%2Fexodus.desync.com%3A6969"],"infoHash":"7fec7ad5d013f50bee6186893d120d2db2a75898","infoHashBuffer":{"type":"Buffer","data":[127,236,122,213,208,19,245,11,238,97,134,137,61,18,13,45,178,167,88,152]},"announce":[],"urlList":[]}}