{"title":"Campeonato Brasileiro de 2005 - IM - Rating A - Final - Thiago M","uid":3421533,"size":508916492,"categoryP":"video","categoryS":"other","magnet":"?xt=urn:btih:80cf5498db12c00f9372672cac3d06109d9d9e00&amp;dn=Campeonato+Brasileiro+de+2005+-+IM+-+Rating+A+-+Final+-+Thiago+M&amp;tr=udp%3A%2F%2Ftracker.openbittorrent.com%3A80&amp;tr=udp%3A%2F%2Fopen.demonii.com%3A1337&amp;tr=udp%3A%2F%2Ftracker.coppersurfer.tk%3A6969&amp;tr=udp%3A%2F%2Fexodus.desync.com%3A6969","seeders":0,"leechers":0,"uploader":"Mazinho","files":1,"time":1134753959,"description":"Final do Campeonato Brasileiro de T&amp;ecirc;nis de Mesa de 2005: Thiago Monteiro x Hugo Hoyama.","torrent":{"xt":"urn:btih:80cf5498db12c00f9372672cac3d06109d9d9e00","amp;dn":"Campeonato+Brasileiro+de+2005+-+IM+-+Rating+A+-+Final+-+Thiago+M","amp;tr":["udp%3A%2F%2Ftracker.openbittorrent.com%3A80","udp%3A%2F%2Fopen.demonii.com%3A1337","udp%3A%2F%2Ftracker.coppersurfer.tk%3A6969","udp%3A%2F%2Fexodus.desync.com%3A6969"],"infoHash":"80cf5498db12c00f9372672cac3d06109d9d9e00","infoHashBuffer":{"type":"Buffer","data":[128,207,84,152,219,18,192,15,147,114,103,44,172,61,6,16,157,157,158,0]},"announce":[],"urlList":[]}}