{"title":"gta password","uid":3415499,"size":1652,"categoryP":"applications","categoryS":"mac","magnet":"?xt=urn:btih:837e948af8f1a46b0c9f50e00df677da07540663&amp;dn=gta+password&amp;tr=udp%3A%2F%2Ftracker.openbittorrent.com%3A80&amp;tr=udp%3A%2F%2Fopen.demonii.com%3A1337&amp;tr=udp%3A%2F%2Ftracker.coppersurfer.tk%3A6969&amp;tr=udp%3A%2F%2Fexodus.desync.com%3A6969","seeders":0,"leechers":1,"uploader":"bashire","files":1,"time":1133318861,"description":"dd","torrent":{"xt":"urn:btih:837e948af8f1a46b0c9f50e00df677da07540663","amp;dn":"gta+password","amp;tr":["udp%3A%2F%2Ftracker.openbittorrent.com%3A80","udp%3A%2F%2Fopen.demonii.com%3A1337","udp%3A%2F%2Ftracker.coppersurfer.tk%3A6969","udp%3A%2F%2Fexodus.desync.com%3A6969"],"infoHash":"837e948af8f1a46b0c9f50e00df677da07540663","infoHashBuffer":{"type":"Buffer","data":[131,126,148,138,248,241,164,107,12,159,80,224,13,246,119,218,7,84,6,99]},"announce":[],"urlList":[]}}