{"title":"DJ Chewmacca! - mix51 - Live Set April 2005","uid":3390219,"size":192849367,"categoryP":"audio","categoryS":"music","magnet":"?xt=urn:btih:8baa98e691da302a0b585f39f662e63f7617645f&amp;dn=DJ+Chewmacca%21+-+mix51+-+Live+Set+April+2005&amp;tr=udp%3A%2F%2Ftracker.openbittorrent.com%3A80&amp;tr=udp%3A%2F%2Fopen.demonii.com%3A1337&amp;tr=udp%3A%2F%2Ftracker.coppersurfer.tk%3A6969&amp;tr=udp%3A%2F%2Fexodus.desync.com%3A6969","seeders":0,"leechers":1,"uploader":"dj_chewmacca","files":8,"time":1128091943,"description":"DJ Chewmacca! - mix51 - Live Set April 2005\n\n1. Red Flag - Pacific Memory (Original Mix)\n2. Leeroy - Destino (Vesiga Club Mix)\n3. Ross Assenheim - In The Past (K90 Remix)\n4. Megara vs DJ Lee - Musical Society (B2 Van Der Karsten Remix)\n5. Shane Tighe &amp; Marlon Juers - The Truth (A1 Extended Mix)\n6. DJ Tatana - Cloudbreaker\n7. Tiesto - Adagio For Strings (Phynn Remix)\n8. DJ Tatana Feat Pee - All That I Feel (DJ Spoke Remix)\n9. Kaste - Desert Eagle (Smith and Pledger Remix)\n10. Xtm and DJ Chucky Present Annia - Give Me Your Love (DJ Silverado Remix)\n11. THD - Dance Again (Xelerator Remix)\n12. Alex Trackone Vs Helmet &amp; Puck - The Universe (Original Mix)\n13. Balearic Bill - Destination (DJ Tiesto Power Mix)","torrent":{"xt":"urn:btih:8baa98e691da302a0b585f39f662e63f7617645f","amp;dn":"DJ+Chewmacca%21+-+mix51+-+Live+Set+April+2005","amp;tr":["udp%3A%2F%2Ftracker.openbittorrent.com%3A80","udp%3A%2F%2Fopen.demonii.com%3A1337","udp%3A%2F%2Ftracker.coppersurfer.tk%3A6969","udp%3A%2F%2Fexodus.desync.com%3A6969"],"infoHash":"8baa98e691da302a0b585f39f662e63f7617645f","infoHashBuffer":{"type":"Buffer","data":[139,170,152,230,145,218,48,42,11,88,95,57,246,98,230,63,118,23,100,95]},"announce":[],"urlList":[]}}