{"title":"Ministry - Rantology [2005]","uid":3375668,"size":134161226,"categoryP":"audio","categoryS":"music","magnet":"?xt=urn:btih:9935eecb2158c2aa7cf8a24a69d424ce5069139b&amp;dn=Ministry+-+Rantology+%5B2005%5D&amp;tr=udp%3A%2F%2Ftracker.openbittorrent.com%3A80&amp;tr=udp%3A%2F%2Fopen.demonii.com%3A1337&amp;tr=udp%3A%2F%2Ftracker.coppersurfer.tk%3A6969&amp;tr=udp%3A%2F%2Fexodus.desync.com%3A6969","seeders":0,"leechers":1,"uploader":"Divxtotal.CoM","files":18,"time":1125191785,"description":"01. No W (Redux)\n02. The Great Satan\n03. Wrong (Update Mix)\n04. N.W.O. (Update Mix)\n05. Stigmata (Update Mix)\n06. Waiting\n07. Warp City (Alternate Mix)\n08. Jesus Built My Hotrod (Update Mix)\n09. Bad Blood (Alternate Mix)\n10. Animosity\n11. Unsung (Alternate Mix)\n12. Bloodlines\n13. Psalm 69 (Live in Paris)\n14. Thieves (Live in Seattle)\n15. The Fall (Live in London)","torrent":{"xt":"urn:btih:9935eecb2158c2aa7cf8a24a69d424ce5069139b","amp;dn":"Ministry+-+Rantology+%5B2005%5D","amp;tr":["udp%3A%2F%2Ftracker.openbittorrent.com%3A80","udp%3A%2F%2Fopen.demonii.com%3A1337","udp%3A%2F%2Ftracker.coppersurfer.tk%3A6969","udp%3A%2F%2Fexodus.desync.com%3A6969"],"infoHash":"9935eecb2158c2aa7cf8a24a69d424ce5069139b","infoHashBuffer":{"type":"Buffer","data":[153,53,238,203,33,88,194,170,124,248,162,74,105,212,36,206,80,105,19,155]},"announce":[],"urlList":[]}}