{"title":"THE.DARK.CHRYSTAL.Dvdr.nordic.Base","uid":3415425,"size":4681416704,"categoryP":"video","categoryS":"movies_dvdr","magnet":"?xt=urn:btih:ac8b9231f85e704b767b9cc9c54c89b0b1aebb33&amp;dn=THE.DARK.CHRYSTAL.Dvdr.nordic.Base&amp;tr=udp%3A%2F%2Ftracker.openbittorrent.com%3A80&amp;tr=udp%3A%2F%2Fopen.demonii.com%3A1337&amp;tr=udp%3A%2F%2Ftracker.coppersurfer.tk%3A6969&amp;tr=udp%3A%2F%2Fexodus.desync.com%3A6969","seeders":0,"leechers":1,"uploader":"basse81","files":1,"time":1133305094,"description":"Ingen extra material och tyv&amp;auml;r inga menyer men jag ska k&amp;ouml;ra med dvd2one f&amp;ouml;r att beh&amp;aring;lla menyerna fram&amp;ouml;ver.\n\n\nLanguage: English\n\nSubtitels: Swedish, Norway, Danish, Finnish\n\nAudio: AC3, 2-ch\n\n\nSci/fic, &amp;auml;ventyr fr&amp;aring;n 1983. Vill veta mer om handlingen kolla p&amp;aring; discshop eller IMBD\n\n\n\n\n\nEnjoy:)","torrent":{"xt":"urn:btih:ac8b9231f85e704b767b9cc9c54c89b0b1aebb33","amp;dn":"THE.DARK.CHRYSTAL.Dvdr.nordic.Base","amp;tr":["udp%3A%2F%2Ftracker.openbittorrent.com%3A80","udp%3A%2F%2Fopen.demonii.com%3A1337","udp%3A%2F%2Ftracker.coppersurfer.tk%3A6969","udp%3A%2F%2Fexodus.desync.com%3A6969"],"infoHash":"ac8b9231f85e704b767b9cc9c54c89b0b1aebb33","infoHashBuffer":{"type":"Buffer","data":[172,139,146,49,248,94,112,75,118,123,156,201,197,76,137,176,177,174,187,51]},"announce":[],"urlList":[]}}