{"title":"Tankard - Zombie Attack (1986) @VBR","uid":3301183,"size":69510501,"categoryP":"audio","categoryS":"music","magnet":"?xt=urn:btih:af0448fca190eb41744c0c190ba3b6e07bbc7130&amp;dn=Tankard+-+Zombie+Attack+%281986%29+%40VBR&amp;tr=udp%3A%2F%2Ftracker.openbittorrent.com%3A80&amp;tr=udp%3A%2F%2Fopen.demonii.com%3A1337&amp;tr=udp%3A%2F%2Ftracker.coppersurfer.tk%3A6969&amp;tr=udp%3A%2F%2Fexodus.desync.com%3A6969","seeders":0,"leechers":1,"uploader":"Zwiebelchen","files":10,"time":1110657753,"description":"Thrash Metal","torrent":{"xt":"urn:btih:af0448fca190eb41744c0c190ba3b6e07bbc7130","amp;dn":"Tankard+-+Zombie+Attack+%281986%29+%40VBR","amp;tr":["udp%3A%2F%2Ftracker.openbittorrent.com%3A80","udp%3A%2F%2Fopen.demonii.com%3A1337","udp%3A%2F%2Ftracker.coppersurfer.tk%3A6969","udp%3A%2F%2Fexodus.desync.com%3A6969"],"infoHash":"af0448fca190eb41744c0c190ba3b6e07bbc7130","infoHashBuffer":{"type":"Buffer","data":[175,4,72,252,161,144,235,65,116,76,12,25,11,163,182,224,123,188,113,48]},"announce":[],"urlList":[]}}