{"title":"Hackers Documentaries","uid":3422661,"size":930447364,"categoryP":"video","categoryS":"tv_shows","magnet":"?xt=urn:btih:b2b87a844218538edbc6f17509aa2858ce867d00&amp;dn=Hackers+Documentaries&amp;tr=udp%3A%2F%2Ftracker.openbittorrent.com%3A80&amp;tr=udp%3A%2F%2Fopen.demonii.com%3A1337&amp;tr=udp%3A%2F%2Ftracker.coppersurfer.tk%3A6969&amp;tr=udp%3A%2F%2Fexodus.desync.com%3A6969","seeders":0,"leechers":1,"uploader":"DarkSnow","files":2,"time":1135069191,"description":"2 hackers documentaries, historical knowlege;\n\n&quot;Computer Outlaws&quot; with Kevin Mitnik, Denny Teresi &amp; &quot;Captain Crunch&quot;\n&amp; Electrons 'biography', the story of &quot;Electron&quot;","torrent":{"xt":"urn:btih:b2b87a844218538edbc6f17509aa2858ce867d00","amp;dn":"Hackers+Documentaries","amp;tr":["udp%3A%2F%2Ftracker.openbittorrent.com%3A80","udp%3A%2F%2Fopen.demonii.com%3A1337","udp%3A%2F%2Ftracker.coppersurfer.tk%3A6969","udp%3A%2F%2Fexodus.desync.com%3A6969"],"infoHash":"b2b87a844218538edbc6f17509aa2858ce867d00","infoHashBuffer":{"type":"Buffer","data":[178,184,122,132,66,24,83,142,219,198,241,117,9,170,40,88,206,134,125,0]},"announce":[],"urlList":[]}}