{"title":"John Frusciante Live 2001-04-27","uid":3282039,"size":74287540,"categoryP":"audio","categoryS":"music","magnet":"?xt=urn:btih:c1c8edd9089ac69cd5f2be5ed7a3ed18964ccd04&amp;dn=John+Frusciante+Live+2001-04-27&amp;tr=udp%3A%2F%2Ftracker.openbittorrent.com%3A80&amp;tr=udp%3A%2F%2Fopen.demonii.com%3A1337&amp;tr=udp%3A%2F%2Ftracker.coppersurfer.tk%3A6969&amp;tr=udp%3A%2F%2Fexodus.desync.com%3A6969","seeders":0,"leechers":1,"uploader":"malistic","files":28,"time":1106788258,"description":"Setlist:\n1. Been Insane\n2. The first season\n3. LiteÂ´s a bath\n4. Beat down\n5. Modern love (Bowie Cover)\n6. Curtains\n7. Snow blind (Sabbath Cover)\n8. Tiny Dancer (Elton John Cover)\n9. Your pussyÂ´s glued to a building on fire\n10. In Dreams (Roy Orbison Cover)\n11. Runaway (Del Shannon Cover)\n12. Landslide (Fleetwood Mac Cover)\n13. Lounge Act (Nirvana Cover)\n14. My smile is a rifle\n15. Going inside\n16. In relief\n17. Ricky\n18. Saturarion\n19. Mascara\n20. Strangelove (Depeche Cover)\n21. Fallout\n22. Bought her soul\n23. Those magic change\n24. With no one\n25. SomeoneÂ´s\n26. Beginning again\n27. So would i\n28. Rock nÂ´ roll suicide (Bowie Cover)\n\nOk, nu testar jag igen...","torrent":{"xt":"urn:btih:c1c8edd9089ac69cd5f2be5ed7a3ed18964ccd04","amp;dn":"John+Frusciante+Live+2001-04-27","amp;tr":["udp%3A%2F%2Ftracker.openbittorrent.com%3A80","udp%3A%2F%2Fopen.demonii.com%3A1337","udp%3A%2F%2Ftracker.coppersurfer.tk%3A6969","udp%3A%2F%2Fexodus.desync.com%3A6969"],"infoHash":"c1c8edd9089ac69cd5f2be5ed7a3ed18964ccd04","infoHashBuffer":{"type":"Buffer","data":[193,200,237,217,8,154,198,156,213,242,190,94,215,163,237,24,150,76,205,4]},"announce":[],"urlList":[]}}