{"title":"Foetus - Blow (2001)","uid":3311036,"size":147237047,"categoryP":"audio","categoryS":"music","magnet":"?xt=urn:btih:c314919b875190cb12930383b07576dbcbb50ea8&amp;dn=Foetus+-+Blow+%282001%29&amp;tr=udp%3A%2F%2Ftracker.openbittorrent.com%3A80&amp;tr=udp%3A%2F%2Fopen.demonii.com%3A1337&amp;tr=udp%3A%2F%2Ftracker.coppersurfer.tk%3A6969&amp;tr=udp%3A%2F%2Fexodus.desync.com%3A6969","seeders":0,"leechers":2,"uploader":"NeedMachine","files":12,"time":1112543912,"description":"Foetus - Blow (2001)\n--------------------------\n\nFlow remixes\n\n\n320kpbs, constant bitrate","torrent":{"xt":"urn:btih:c314919b875190cb12930383b07576dbcbb50ea8","amp;dn":"Foetus+-+Blow+%282001%29","amp;tr":["udp%3A%2F%2Ftracker.openbittorrent.com%3A80","udp%3A%2F%2Fopen.demonii.com%3A1337","udp%3A%2F%2Ftracker.coppersurfer.tk%3A6969","udp%3A%2F%2Fexodus.desync.com%3A6969"],"infoHash":"c314919b875190cb12930383b07576dbcbb50ea8","infoHashBuffer":{"type":"Buffer","data":[195,20,145,155,135,81,144,203,18,147,3,131,176,117,118,219,203,181,14,168]},"announce":[],"urlList":[]}}