{"title":"Scorpius.Gigantus.2005.FS.DVDSCR.XviD-PuRE","uid":3414938,"size":745382658,"categoryP":"video","categoryS":"movies","magnet":"?xt=urn:btih:c526958852cfe7909e98ce5fd4c97b462c4a390d&amp;dn=_Scorpius.Gigantus.2005.FS.DVDSCR.XviD-PuRE&amp;tr=udp%3A%2F%2Ftracker.openbittorrent.com%3A80&amp;tr=udp%3A%2F%2Fopen.demonii.com%3A1337&amp;tr=udp%3A%2F%2Ftracker.coppersurfer.tk%3A6969&amp;tr=udp%3A%2F%2Fexodus.desync.com%3A6969","seeders":0,"leechers":1,"uploader":"masseur","files":53,"time":1133204222,"description":"www.NewTorrents.info","torrent":{"xt":"urn:btih:c526958852cfe7909e98ce5fd4c97b462c4a390d","amp;dn":"_Scorpius.Gigantus.2005.FS.DVDSCR.XviD-PuRE","amp;tr":["udp%3A%2F%2Ftracker.openbittorrent.com%3A80","udp%3A%2F%2Fopen.demonii.com%3A1337","udp%3A%2F%2Ftracker.coppersurfer.tk%3A6969","udp%3A%2F%2Fexodus.desync.com%3A6969"],"infoHash":"c526958852cfe7909e98ce5fd4c97b462c4a390d","infoHashBuffer":{"type":"Buffer","data":[197,38,149,136,82,207,231,144,158,152,206,95,212,201,123,70,44,74,57,13]},"announce":[],"urlList":[]}}