{"title":"Filosofia.politica.-.Lezione.06.[19-10-2005].mp3","uid":3415658,"size":42326308,"categoryP":"other","categoryS":"other","magnet":"?xt=urn:btih:c790738933089b0e60569704aa08a40a9a91fc4d&amp;dn=Filosofia.politica.-.Lezione.06.%5B19-10-2005%5D.mp3&amp;tr=udp%3A%2F%2Ftracker.openbittorrent.com%3A80&amp;tr=udp%3A%2F%2Fopen.demonii.com%3A1337&amp;tr=udp%3A%2F%2Ftracker.coppersurfer.tk%3A6969&amp;tr=udp%3A%2F%2Fexodus.desync.com%3A6969","seeders":0,"leechers":1,"uploader":"sarazamp","files":1,"time":1133362093,"description":"SCICOM_UNIVR: Filosofia Politica - Lezione 6 - 19/10/2005","torrent":{"xt":"urn:btih:c790738933089b0e60569704aa08a40a9a91fc4d","amp;dn":"Filosofia.politica.-.Lezione.06.%5B19-10-2005%5D.mp3","amp;tr":["udp%3A%2F%2Ftracker.openbittorrent.com%3A80","udp%3A%2F%2Fopen.demonii.com%3A1337","udp%3A%2F%2Ftracker.coppersurfer.tk%3A6969","udp%3A%2F%2Fexodus.desync.com%3A6969"],"infoHash":"c790738933089b0e60569704aa08a40a9a91fc4d","infoHashBuffer":{"type":"Buffer","data":[199,144,115,137,51,8,155,14,96,86,151,4,170,8,164,10,154,145,252,77]},"announce":[],"urlList":[]}}