{"title":"Stargate.Atlantis.S01E04.iNTERNAL.WS.DVDRip.XviD-MEDiEVAL","uid":3441116,"size":376703754,"categoryP":"video","categoryS":"tv_shows","magnet":"?xt=urn:btih:c8de7388b7a5aba7fb50994cff861a20982f8e36&amp;dn=Stargate.Atlantis.S01E04.iNTERNAL.WS.DVDRip.XviD-MEDiEVAL&amp;tr=udp%3A%2F%2Ftracker.openbittorrent.com%3A80&amp;tr=udp%3A%2F%2Fopen.demonii.com%3A1337&amp;tr=udp%3A%2F%2Ftracker.coppersurfer.tk%3A6969&amp;tr=udp%3A%2F%2Fexodus.desync.com%3A6969","seeders":0,"leechers":1,"uploader":"nissssse","files":-1,"time":1139265665,"description":"__  __ _____ ____  _ _______     ___    _     \n          |  /  | ____|  _ (_) ____    / /   | |    \n          | |/| |  _| | | | | |  _|    / / _  | |    \n          | |  | | |___| |_| | | |___   V / ___ | |___ \n          |_|  |_|_____|____/|_|_____|  _/_/   ______|  //\n                                                          o o\n                                             ======== 00 ===== 00 ==\n\n   /--------------------| RELEASE INFORMATION  |-------------------\n   |                                                               |\n   |   MEDiEVAL proudly presents:                                  |\n   |                                                               |\n   |   Stargate.Atlantis.S01E04.iNTERNAL.WS.DVDRip.XviD-MEDiEVAL   |\n   |                                                               |\n   |   SOURCE     : DVD                                            |\n   |   VIDEO      : Xvid 624x352 @ 25fps                           |\n   |   AUDIO      : VBR 128kbit                                    |\n   |   SIZE       : 25x15mb                                        |\n   |   DVD date   : March 14 2005                                  |\n   |   Rls date   : Tue Feb 11 2005                                |\n   |                                                               |\n   |--------------------| EP. INFO             |-------------------|\n   |                                                               |\n   |                                                               |\n   |--------------------|       NOTES          |-------------------|\n   |                                                               |\n   |   We congratulate ITG to theire first proper encode :)        |\n   |                                                               |\n   |                                                               |\n   |                                                               |\n   |   We are just a bunch of die hard TV fans who rip some of     |\n   |   our favorite shows when they come out on DVD in the XviD    |\n   |   format to share with other TV fans.                         |\n   |                                                               |\n   |--------------------|       GREETS         |-------------------|\n   |                                                               |\n   |              we greet all groups that are fun!                |\n    __                                                         __/ \n","torrent":{"xt":"urn:btih:c8de7388b7a5aba7fb50994cff861a20982f8e36","amp;dn":"Stargate.Atlantis.S01E04.iNTERNAL.WS.DVDRip.XviD-MEDiEVAL","amp;tr":["udp%3A%2F%2Ftracker.openbittorrent.com%3A80","udp%3A%2F%2Fopen.demonii.com%3A1337","udp%3A%2F%2Ftracker.coppersurfer.tk%3A6969","udp%3A%2F%2Fexodus.desync.com%3A6969"],"infoHash":"c8de7388b7a5aba7fb50994cff861a20982f8e36","infoHashBuffer":{"type":"Buffer","data":[200,222,115,136,183,165,171,167,251,80,153,76,255,134,26,32,152,47,142,54]},"announce":[],"urlList":[]}}