{"title":"Edith - Much To Cry About","uid":3441133,"size":29559052,"categoryP":"video","categoryS":"music_videos","magnet":"?xt=urn:btih:ca9d21064612bec1649d485a4cd3edccde0ce4ab&amp;dn=Edith+-+Much+To+Cry+About&amp;tr=udp%3A%2F%2Ftracker.openbittorrent.com%3A80&amp;tr=udp%3A%2F%2Fopen.demonii.com%3A1337&amp;tr=udp%3A%2F%2Ftracker.coppersurfer.tk%3A6969&amp;tr=udp%3A%2F%2Fexodus.desync.com%3A6969","seeders":0,"leechers":1,"uploader":"RosaMannen","files":1,"time":1139266180,"description":"Great swedish pop music. Check this out.\n\n.ooOO ROSA MANNEN 2006 OOoo.","torrent":{"xt":"urn:btih:ca9d21064612bec1649d485a4cd3edccde0ce4ab","amp;dn":"Edith+-+Much+To+Cry+About","amp;tr":["udp%3A%2F%2Ftracker.openbittorrent.com%3A80","udp%3A%2F%2Fopen.demonii.com%3A1337","udp%3A%2F%2Ftracker.coppersurfer.tk%3A6969","udp%3A%2F%2Fexodus.desync.com%3A6969"],"infoHash":"ca9d21064612bec1649d485a4cd3edccde0ce4ab","infoHashBuffer":{"type":"Buffer","data":[202,157,33,6,70,18,190,193,100,157,72,90,76,211,237,204,222,12,228,171]},"announce":[],"urlList":[]}}