{"title":"Babysitter Caught With Wet Panties[XviD]","uid":3395805,"size":55308894,"categoryP":"porn","categoryS":"movie_clips","magnet":"?xt=urn:btih:caac9f12180a36a0559dbb20aeeeba3d78599ab8&amp;dn=Babysitter+Caught+With+Wet+Panties%5BXviD%5D&amp;tr=udp%3A%2F%2Ftracker.openbittorrent.com%3A80&amp;tr=udp%3A%2F%2Fopen.demonii.com%3A1337&amp;tr=udp%3A%2F%2Ftracker.coppersurfer.tk%3A6969&amp;tr=udp%3A%2F%2Fexodus.desync.com%3A6969","seeders":0,"leechers":2,"uploader":"flop4ever","files":1,"time":1129171236,"description":"Babysitter Caught With Wet Panties[XviD]\n\n \n&quot;Babysitter Krissie is touching her wet panties when Mr. Smith walks in. He notices her wet panties and licks and sucks her wet pussy until he blows a load on her panties.&quot;\n\n\nScreens: http://fapomatic.com/show.php?loc=61&amp;f=babysitter_twip.jpg","torrent":{"xt":"urn:btih:caac9f12180a36a0559dbb20aeeeba3d78599ab8","amp;dn":"Babysitter+Caught+With+Wet+Panties%5BXviD%5D","amp;tr":["udp%3A%2F%2Ftracker.openbittorrent.com%3A80","udp%3A%2F%2Fopen.demonii.com%3A1337","udp%3A%2F%2Ftracker.coppersurfer.tk%3A6969","udp%3A%2F%2Fexodus.desync.com%3A6969"],"infoHash":"caac9f12180a36a0559dbb20aeeeba3d78599ab8","infoHashBuffer":{"type":"Buffer","data":[202,172,159,18,24,10,54,160,85,157,187,32,174,238,186,61,120,89,154,184]},"announce":[],"urlList":[]}}