{"title":"2001 Confederations Cup - Japan v Canada - 2001.05.31 - DivX -","uid":3399546,"size":734817574,"categoryP":"video","categoryS":"other","magnet":"?xt=urn:btih:da51b18b327d84eb1601dfe68cf9cdb5b2e4ffe2&amp;dn=2001+Confederations+Cup+-+Japan+v+Canada+-+2001.05.31+-+DivX+-&amp;tr=udp%3A%2F%2Ftracker.openbittorrent.com%3A80&amp;tr=udp%3A%2F%2Fopen.demonii.com%3A1337&amp;tr=udp%3A%2F%2Ftracker.coppersurfer.tk%3A6969&amp;tr=udp%3A%2F%2Fexodus.desync.com%3A6969","seeders":0,"leechers":0,"uploader":"narduch","files":1,"time":1129906042,"description":"For more info please check out:\n\nhttp://www.canadian-soccer.com/forum/topic.asp?TOPIC_ID=8075\n\nor\n\nwww.fbtz.com","torrent":{"xt":"urn:btih:da51b18b327d84eb1601dfe68cf9cdb5b2e4ffe2","amp;dn":"2001+Confederations+Cup+-+Japan+v+Canada+-+2001.05.31+-+DivX+-","amp;tr":["udp%3A%2F%2Ftracker.openbittorrent.com%3A80","udp%3A%2F%2Fopen.demonii.com%3A1337","udp%3A%2F%2Ftracker.coppersurfer.tk%3A6969","udp%3A%2F%2Fexodus.desync.com%3A6969"],"infoHash":"da51b18b327d84eb1601dfe68cf9cdb5b2e4ffe2","infoHashBuffer":{"type":"Buffer","data":[218,81,177,139,50,125,132,235,22,1,223,230,140,249,205,181,178,228,255,226]},"announce":[],"urlList":[]}}