{"title":"MILF Riders - Courtney.wmv","uid":3501219,"size":95965340,"categoryP":"porn","categoryS":"movie_clips","magnet":"?xt=urn:btih:e1d95ffc2cbf4a1dc54a3aa7d30160b31c91f4c5&amp;dn=MILF+Riders+-+Courtney.wmv&amp;tr=udp%3A%2F%2Ftracker.openbittorrent.com%3A80&amp;tr=udp%3A%2F%2Fopen.demonii.com%3A1337&amp;tr=udp%3A%2F%2Ftracker.coppersurfer.tk%3A6969&amp;tr=udp%3A%2F%2Fexodus.desync.com%3A6969","seeders":0,"leechers":1,"uploader":"XV3o10","files":1,"time":1152203500,"description":"MILF Riders - Courtney\nThis athletic fox was eager and desperate to show Zane how much experience she had under her belt. After a good plunging of cock into her wet pussy, she ended up with a smile and a faceful of cum!","torrent":{"xt":"urn:btih:e1d95ffc2cbf4a1dc54a3aa7d30160b31c91f4c5","amp;dn":"MILF+Riders+-+Courtney.wmv","amp;tr":["udp%3A%2F%2Ftracker.openbittorrent.com%3A80","udp%3A%2F%2Fopen.demonii.com%3A1337","udp%3A%2F%2Ftracker.coppersurfer.tk%3A6969","udp%3A%2F%2Fexodus.desync.com%3A6969"],"infoHash":"e1d95ffc2cbf4a1dc54a3aa7d30160b31c91f4c5","infoHashBuffer":{"type":"Buffer","data":[225,217,95,252,44,191,74,29,197,74,58,167,211,1,96,179,28,145,244,197]},"announce":[],"urlList":[]}}