{"title":"The Princess Has Come Of Age[emulebit]","uid":3467744,"size":419083810,"categoryP":"porn","categoryS":"movies","magnet":"?xt=urn:btih:f88361587ce4107774c8a450a6ef2f43c0d0e48a&amp;dn=The+Princess+Has+Come+Of+Age%5Bemulebit%5D&amp;tr=udp%3A%2F%2Ftracker.openbittorrent.com%3A80&amp;tr=udp%3A%2F%2Fopen.demonii.com%3A1337&amp;tr=udp%3A%2F%2Ftracker.coppersurfer.tk%3A6969&amp;tr=udp%3A%2F%2Fexodus.desync.com%3A6969","seeders":0,"leechers":1,"uploader":"cucaracha","files":1,"time":1144410690,"description":"go www.emulebit.com forum for screenshots!","torrent":{"xt":"urn:btih:f88361587ce4107774c8a450a6ef2f43c0d0e48a","amp;dn":"The+Princess+Has+Come+Of+Age%5Bemulebit%5D","amp;tr":["udp%3A%2F%2Ftracker.openbittorrent.com%3A80","udp%3A%2F%2Fopen.demonii.com%3A1337","udp%3A%2F%2Ftracker.coppersurfer.tk%3A6969","udp%3A%2F%2Fexodus.desync.com%3A6969"],"infoHash":"f88361587ce4107774c8a450a6ef2f43c0d0e48a","infoHashBuffer":{"type":"Buffer","data":[248,131,97,88,124,228,16,119,116,200,164,80,166,239,47,67,192,208,228,138]},"announce":[],"urlList":[]}}